cli_tictactoe/__init__.py
cli_tictactoe/main.py
cli_tictactoe/scripts/__init__.py
cli_tictactoe/scripts/run.py
cli_tictactoe-1.0.4.dist-info/METADATA
cli_tictactoe-1.0.4.dist-info/WHEEL
cli_tictactoe-1.0.4.dist-info/entry_points.txt
cli_tictactoe-1.0.4.dist-info/top_level.txt
cli_tictactoe-1.0.4.dist-info/RECORD
